ptscripts/__init__.py
ptscripts/__main__.py
ptscripts/logs.py
ptscripts/models.py
ptscripts/parser.py
ptscripts/process.py
ptscripts/py.typed
ptscripts/utils.py
ptscripts/version.py
ptscripts/virtualenv.py
python_tools_scripts-0.20.5.dist-info/LICENSE
python_tools_scripts-0.20.5.dist-info/METADATA
python_tools_scripts-0.20.5.dist-info/WHEEL
python_tools_scripts-0.20.5.dist-info/entry_points.txt
python_tools_scripts-0.20.5.dist-info/top_level.txt
python_tools_scripts-0.20.5.dist-info/RECORD
