Metadata-Version: 2.1
Name: python-tools-scripts
Version: 0.20.5
Summary: Python Tools Scripts
Home-page: https://github.com/s0undt3ch/python-tools-scripts
Author: Pedro Algarvio
Author-email: pedro@algarvio.me
License: Apache Software License 2.0
Project-URL: Source, https://github.com/s0undt3ch/python-tools-scripts
Project-URL: Tracker, https://github.com/s0undt3ch/python-tools-scripts/issues
Project-URL: Documentation, https://python-tools-scripts.readthedocs.io
Platform: unix
Platform: linux
Platform: osx
Platform: cygwin
Platform: win32
Classifier: Programming Language :: Python
Classifier: Programming Language :: Cython
Classifier: Programming Language :: Python :: 3
Classifier: Programming Language :: Python :: 3 :: Only
Classifier: Programming Language :: Python :: 3.9
Classifier: Development Status :: 5 - Production/Stable
Classifier: Intended Audience :: Developers
Classifier: License :: OSI Approved :: Apache Software License
Requires-Python: >=3.9
License-File: LICENSE
Requires-Dist: attrs
Requires-Dist: pydantic >=2.0
Requires-Dist: rich
Requires-Dist: requests >=2.31.0
Requires-Dist: filelock
Requires-Dist: typing-extensions ; python_version < "3.11"
Provides-Extra: changelog
Requires-Dist: towncrier ==22.12.0 ; extra == 'changelog'
Provides-Extra: docs
Requires-Dist: furo ; extra == 'docs'
Requires-Dist: sphinx ; extra == 'docs'
Requires-Dist: sphinx-copybutton ; extra == 'docs'
Requires-Dist: sphinx-prompt ; extra == 'docs'
Requires-Dist: sphinxcontrib-spelling ; extra == 'docs'
Requires-Dist: sphinxcontrib-towncrier >=0.3.0a0 ; extra == 'docs'
Provides-Extra: lint
Requires-Dist: black ; extra == 'lint'
Requires-Dist: reorder-python-imports ; extra == 'lint'
Requires-Dist: flake8 >=5.0.4 ; extra == 'lint'
Requires-Dist: flake8-mypy-fork ; extra == 'lint'
Requires-Dist: flake8-docstrings ; extra == 'lint'
Requires-Dist: flake8-typing-imports ; extra == 'lint'
Provides-Extra: poetry
Requires-Dist: poetry >=1.8.0 ; extra == 'poetry'
Requires-Dist: poetry-plugin-export ; extra == 'poetry'
Provides-Extra: tests
Requires-Dist: pytest ; extra == 'tests'
